pyli/__init__.py
pyli/main.py
pyli/preamble.py
pyli/refs.py
pyli/spec.py
pyli/util.py
pyli-2.0.2.dist-info/licenses/LICENSE
pyli-2.0.2.dist-info/METADATA
pyli-2.0.2.dist-info/WHEEL
pyli-2.0.2.dist-info/entry_points.txt
pyli-2.0.2.dist-info/top_level.txt
pyli-2.0.2.dist-info/RECORD
