Metadata-Version: 2.4
Name: pyli
Version: 2.0.2
Summary: Better python CLI integration
Author-email: thenoviceoof <thenoviceoof@gmail.com>
License: Copyright (c) <2014> <thenoviceoof>
Project-URL: Repository, https://github.com/thenoviceoof/pyli
Project-URL: Issues, https://github.com/thenoviceoof/pyli/issues
Classifier: Programming Language :: Python :: 3
Classifier: Programming Language :: Python :: 3.9
Classifier: License :: OSI Approved :: MIT License
Classifier: Operating System :: OS Independent
Requires-Python: >3.0
License-File: LICENSE
Dynamic: license-file
